python_bmp_generator/__init__.py
python_bmp_generator/__main__.py
python_bmp_generator/bmp_header.py
python_bmp_generator/bmp_info_header.py
python_bmp_generator/create_bmp.py
python_bmp_generator-0.1.0.dist-info/LICENSE
python_bmp_generator-0.1.0.dist-info/METADATA
python_bmp_generator-0.1.0.dist-info/WHEEL
python_bmp_generator-0.1.0.dist-info/entry_points.txt
python_bmp_generator-0.1.0.dist-info/top_level.txt
python_bmp_generator-0.1.0.dist-info/RECORD
