Metadata-Version: 2.1
Name: python-bmp-generator
Version: 0.1.0
Summary: Generate bitmap images
Author-email: Matt Ettler <mattettler@protonmail.com>
Project-URL: Homepage, https://github.com/MattEttler/python-bmp-generator
Project-URL: Bug Tracker, https://github.com/MattEttler/python-bmp-generator/issues
Classifier: Programming Language :: Python :: 3
Classifier: License :: OSI Approved :: MIT License
Classifier: Operating System :: OS Independent
Requires-Python: >=3.11.2
License-File: LICENSE
